fixworker/__init__.py
fixworker/__main__.py
fixworker/cleanup.py
fixworker/collect.py
fixworker/config.py
fixworker/exceptions.py
fixworker/fixcore.py
fixworker/pluginloader.py
fixworker/tag.py
fixworker/utils.py
test/__init__.py
test/fakeconfig.py
test/test_args.py
test/test_collect.py
test/test_fixcore.py
test/test_utils.py
fixinventoryworker-4.2.0.dist-info/METADATA
fixinventoryworker-4.2.0.dist-info/WHEEL
fixinventoryworker-4.2.0.dist-info/entry_points.txt
fixinventoryworker-4.2.0.dist-info/top_level.txt
fixinventoryworker-4.2.0.dist-info/RECORD
