Metadata-Version: 2.1
Name: fixinventoryworker
Version: 4.2.0
Summary: Runs collector plugins and sends the result to fixcore.
Author: Some Engineering Inc.
License: AGPLv3
Project-URL: Documentation, https://inventory.fix.security
Project-URL: Source, https://github.com/someengineering/fix/tree/main/fixworker
Classifier: Programming Language :: Python :: 3
Requires-Python: >=3.12
Requires-Dist: fixinventorylib==4.2.0
Requires-Dist: tenacity
Requires-Dist: CherryPy
